{
"pins":
  {
  "1":
    {	
      "layout": 
      {
        "pad": "pad", 
        "location": [-2.7, 1.905],
        "label": "SHDN"
      }
    },
  "2":
    {	
      "layout": 
      {
        "pad": "pad", 
        "location": [-2.7, 0.635],
        "label": "BYPADD"
      }
    },
  "3":
    {	
      "layout": 
      {
        "pad": "pad", 
        "location": [-2.7, -0.635],
        "label": "IN+"
      }
    },
  "4":
    {	
      "layout": 
      {
        "pad": "pad", 
        "location": [-2.7, -1.905],
        "label": "IN-"
      }
    },
  "5":
    {	
      "layout": 
      {
        "pad": "pad", 
        "location": [2.7, -1.905],
        "label": "Vo+"
      }
    },
  "6":
    {	
      "layout": 
      {
        "pad": "pad", 
        "location": [2.7, -0.635],
        "label": "VDD"
      }
    },
  "7":
    {	
      "layout": 
      {
        "pad": "pad", 
        "location": [2.7, 0.635],
        "label": "GND"
      }
    },
  "8":
    {	
      "layout": 
      {
        "pad": "pad", 
        "location": [2.7, 1.905],
        "label": "Vo-"
      }
    }
  },
  "layout":
  {
    "silkscreen":
    {
      "shapes":
      [
        {
          "type": "path",
          "layers": ["top"],
          "value": "m -21.015083,-30.007609 c -0.01603,0.0016 -0.03111,0.0084 -0.043,0.01929 -3.58e-4,3.33e-4 -7.53e-4,7.67e-4 -0.0011,0.0011 -0.01078,0.01026 -0.01827,0.0235 -0.0215,0.03803 -0.0032,0.01452 -0.0021,0.02968 0.0033,0.04355 1.58e-4,4.08e-4 3.89e-4,7.01e-4 5.53e-4,0.0011 0.006,0.01488 0.01664,0.02744 0.03032,0.03583 l 0.527513,0.32191 0,4.728876 -0.102526,0.06229 -0.356636,0.218281 -0.06835,0.04134 c -0.01426,0.0089 -0.02513,0.02226 -0.03087,0.03803 -1.44e-4,4.09e-4 -4.1e-4,6.96e-4 -5.51e-4,0.0011 -0.005,0.0146 -0.0054,0.03038 -0.0011,0.0452 l 0,5.51e-4 c 0.0041,0.0142 0.01239,0.02685 0.0237,0.03638 l 0.0011,5.51e-4 c 5.42e-4,4.54e-4 0.0011,6.7e-4 0.0017,0.0011 0.01291,0.01013 0.02879,0.01575 0.0452,0.01599 l 4.500121,0 c 0.01622,-3.61e-4 0.03189,-0.006 0.04465,-0.01599 0.0011,-8.61e-4 0.0022,-0.0013 0.0033,-0.0022 0.01111,-0.0096 0.01916,-0.02225 0.02315,-0.03638 0.0043,-0.01482 0.0039,-0.03061 -0.0011,-0.0452 l 0,-5.52e-4 -5.5e-4,-5.51e-4 c -0.0057,-0.01577 -0.01661,-0.02917 -0.03087,-0.03803 l -0.529166,-0.321909 0,-4.682023 0,-0.04685 0.328523,-0.19954 0.200643,-0.12237 c 0.01426,-0.0089 0.02513,-0.02226 0.03087,-0.03803 l 5.5e-4,-5.51e-4 0,-5.51e-4 c 0.005,-0.01459 0.0054,-0.03038 0.0011,-0.0452 l 0,-5.51e-4 c -0.0041,-0.0142 -0.01239,-0.02685 -0.0237,-0.03638 l -5.51e-4,-5.52e-4 c -5.47e-4,-4.55e-4 -0.0011,-6.67e-4 -0.0017,-0.0011 -0.01291,-0.01013 -0.02879,-0.01574 -0.0452,-0.01598 l -4.500121,0 -0.0077,0 z m 0.472389,0.150481 0.600275,0 2.794111,2.794662 0,0.600273 -3.394386,-3.394935 z m 0.9525,0 0.574918,0 1.866968,1.866967 0,0.574366 -2.441886,-2.441333 z m 1.282127,0 0.601376,0 0.558383,0.558382 0,0.601375 -1.159759,-1.159757 z m 0.953053,0 0.574918,0 0.0017,0.0022 -0.332381,0.203399 c -0.0081,0.0047 -0.01516,0.01088 -0.02095,0.01819 l -0.223241,-0.223242 0,-5.52e-4 z m -3.013495,0.881394 3.220201,3.221302 0,0.574366 -3.220201,-3.2202 0,-0.575468 z m 0,0.929349 3.220201,3.220199 0,0.04906 c 1.61e-4,0.02662 0.01443,0.05117 0.03748,0.06449 l 0.195681,0.119613 0.08544,0.08544 -0.600823,0 -2.937978,-2.938529 0,-0.600273 z m 0,1.307482 2.230769,2.23132 -0.574367,0 -1.656402,-1.656402 0,-0.574918 z m 0,0.927696 1.303624,1.303624 -0.601376,0 -0.702248,-0.702249 0,-0.601375 z m -0.143866,1.164717 0.138904,0.138907 -0.366558,0 0.227654,-0.138907 z",
          "style": "fill",
          "gerber-lp": "dccccccccc"
        },
        { 
          "type": "rect",
          "layers": ["top"],
          "style": "fill",
          "width": 0.65,
          "height": 0.65,
          "location": [-2.0,3.4]
        },
        { 
          "type": "rect",
          "layers": ["top"],
          "style": "fill",
          "width": 3.5,
          "height": 0.65,
          "location": [0.55,3.4]
        }
      ]
    },
    "assembly":
    {
      "shapes":
      [
        {
          "type": "rect",
          "layers": ["top"],
          "width": 4,
          "height": 5
        },
        { 
          "type": "circle",
          "layers": ["top"],
          "style": "fill",
          "diameter": 0.8,
          "location": [-1.2,1.8]
        }
      ]
    }
  },
  "pads":
  {
    "pad":
    {
      "shapes":
      [
        {
          "type": "rect",
          "width": 1.5,
          "height": 0.6,
          "layers": ["top"]
        }
      ]      
    }
  }
}
